{
    "@class": "com.kony.gen.viz.model.container.KVizScrollFlexForm",
    "DNDConfig": null,
    "_margin_": [
        0,
        0,
        0,
        0
    ],
    "_orientation_": 1,
    "_padding_": [
        0,
        0,
        0,
        0
    ],
    "_percent_": true,
    "_skin_": "sac341e541404c78ab4b4d0347de1a2e",
    "_title_": null,
    "addWidgetsdone": false,
    "allboxes": [],
    "canUpdateUI": true,
    "children": [
        "flxBody"
    ],
    "containerId": true,
    "containerweight": 100,
    "currentLocale": "default",
    "device": "GalaxyS5",
    "displayorientation": 3,
    "enabledforidletimeout": false,
    "id": "tmp",
    "info": null,
    "initdone": false,
    "inputaccessoryviewtype": 4,
    "intransitionconfig": {
        "formTransition": "None"
    },
    "isvisible": true,
    "kuid": "f721f0bff3ef44ee867aad9efe8cd53e",
    "name": "kony.ui.Form2",
    "needappmenu": true,
    "outtransitionconfig": {
        "formTransition": "None"
    },
    "paddinginpixel": false,
    "platform": "android",
    "prevDevice": "iPhone6",
    "prevPlatform": "iphone",
    "retainscrollposition": false,
    "shellCSS": "and_GalaxyS5",
    "titleBarSkin": "s4b7bc6b7ff6462e97ea51e118d295bb",
    "titlebar": true,
    "type": 3,
    "wType": "Form"
}