{
    "DNDConfig": null,
    "__parentReadjusting__": false,
    "_height_": {
        "type": "string",
        "value": "50%"
    },
    "_left_": {
        "type": "string",
        "value": "0dp"
    },
    "_margin_": [
        0,
        0,
        0,
        0
    ],
    "_orientation_": 6,
    "_padding_": [
        0,
        0,
        0,
        0
    ],
    "_percent_": true,
    "_skin_": "s88df92a5a594840a086b689ff7f440f",
    "_top_": {
        "type": "string",
        "value": "52dp"
    },
    "_width_": {
        "type": "string",
        "value": "90%"
    },
    "allboxes": [],
    "autogrowmode": 0,
    "canUpdateUI": true,
    "centerx": {
        "type": "string",
        "value": "50%"
    },
    "children": [
        "Image0fa964fba0b2d48",
        "txtNote"
    ],
    "clipbounds": true,
    "containerweight": 100,
    "enablescrolling": true,
    "id": "FlexContainer0f88d034188d44a",
    "info": null,
    "isvisible": true,
    "kuid": "fecd6e2b54d14082a1d094fc028bf773",
    "layouttype": 2,
    "name": "kony.ui.FlexContainer",
    "parent": "flxAddQuickNote",
    "pf": "frmHome",
    "snapgridsize": 10,
    "snaptogrid": true,
    "wType": "FlexContainer",
    "widgetalignment": 1,
    "zindex": 1
}